Metadata-Version: 2.1
Name: reportlab-qrcode
Version: 0.1.6
Summary: Allows to create QR codes for use with the ReportLab PDF library.
Home-page: https://github.com/hprid/reportlab-qrcode
Author: Henning Pridöhl
Author-email: dev@hprid.de
License: MIT
Keywords: qrcode reportlab pdf
Platform: any
Classifier: Development Status :: 4 - Beta
Classifier: License :: OSI Approved :: MIT License
Classifier: Programming Language :: Python :: 3
Classifier: Programming Language :: Python :: 3.6
Classifier: Programming Language :: Python :: 3.7
Classifier: Programming Language :: Python :: 3.8
Classifier: Programming Language :: Python :: 3.9
Classifier: Programming Language :: Python :: 3.10
Classifier: Programming Language :: Python :: 3.11
Requires-Python: >=3.6
License-File: LICENSE
Requires-Dist: qrcode
Requires-Dist: reportlab
Provides-Extra: testing
Requires-Dist: pytest; extra == "testing"
Requires-Dist: pyzbar; extra == "testing"
Requires-Dist: pillow; extra == "testing"
